advanced_macro_calculator/__init__.py
advanced_macro_calculator/__main__.py
advanced_macro_calculator/calculations.py
advanced_macro_calculator/input_handlers.py
advanced_macro_calculator/outputs.py
advanced_macro_calculator-1.0.4.dist-info/LICENSE
advanced_macro_calculator-1.0.4.dist-info/METADATA
advanced_macro_calculator-1.0.4.dist-info/WHEEL
advanced_macro_calculator-1.0.4.dist-info/entry_points.txt
advanced_macro_calculator-1.0.4.dist-info/top_level.txt
advanced_macro_calculator-1.0.4.dist-info/RECORD
