Metadata-Version: 2.1
Name: advanced_macro_calculator
Version: 1.0.4
Summary: An advanced macronutrient and calorie calculator to help achieve desired body composition.
Author: Michael Trovato
Author-email: mtrovato@advancedmacrocalculator.com
License: MIT
Project-URL: Website, https://advancedmacrocalculator.com
Project-URL: Source, https://github.com/michael-trovato/advanced-macro-calculator
Project-URL: Tracker, https://github.com/michael-trovato/advanced-macro-calculator/issues
Classifier: Programming Language :: Python :: 3
Classifier: License :: OSI Approved :: MIT License
Classifier: Operating System :: OS Independent
Requires-Python: >=3.6
License-File: LICENSE
